{
  "id": "fantom-testnet",
  "shortName": "Fantom",
  "fullName": "Fantom Testnet",
  "aliases": ["evm-4002"],
  "caip2Id": "eip155:4002",
  "graphNode": { "protocol": "ethereum" },
  "explorerUrls": ["https://testnet.ftmscan.com"],
  "rpcUrls": ["https://rpc.testnet.fantom.network"],
  "apiUrls": [
    {
      "url": "https://fantom-testnet.abi.pinax.network/api",
      "kind": "etherscan"
    }
  ],
  "services": { "subgraphs": ["https://api.studio.thegraph.com/deploy"] },
  "networkType": "testnet",
  "relations": [{ "kind": "testnetOf", "network": "fantom" }],
  "issuanceRewards": false,
  "nativeToken": "FTM",
  "docsUrl": "https://docs.fantom.foundation",
  "genesis": {
    "hash": "0x00000000000000009a0c7349d44dc4d0f602a54e0a8543360c2fee4c3937b49e",
    "height": 0
  },
  "firehose": {
    "blockType": "sf.ethereum.type.v2.Block",
    "evmExtendedModel": false,
    "bufUrl": "https://buf.build/streamingfast/firehose-ethereum",
    "bytesEncoding": "hex"
  },
  "icon": { "web3Icons": { "name": "fantom" } }
}
